{"title":"POCLANOS ─ Album","url":"https://poclanos.com/album-list/","favicon":"https://poclanos.com/drmvsn/wp-content/uploads/2020/08/Android-Chrome-home_196x196-96x96.png","elements":[{"title":"Loner Lover (還好有人跟我一樣)","contents":"Sweet John (甜約翰)","link":"https://poclanos.com/album/loner-lover-%e9%82%84%e5%a5%bd%e6%9c%89%e4%ba%ba%e8%b7%9f%e6%88%91%e4%b8%80%e6%a8%a3/","retrieved":1710385861334,"image":"https://poclanos.com/drmvsn/wp-content/uploads/2024/03/4.-%EC%BB%A4%EB%B2%84-Sweet-John-%E7%94%9C%E7%B4%84%E7%BF%B0-Loner-Lover-%E9%82%84%E5%A5%BD%E6%9C%89%E4%BA%BA%E8%B7%9F%E6%88%91%E4%B8%80%E6%A8%A3-600x600.jpg"},{"title":"Give It To Me","contents":"Dolphin Pants Brothers","link":"https://poclanos.com/album/give-it-to-me/","retrieved":1710385861334,"image":"https://poclanos.com/drmvsn/wp-content/uploads/2024/03/%ED%81%AC%EA%B8%B0%EB%B3%80%ED%99%98dpb_giveittome-600x600.jpg"},{"title":"Celebrate","contents":"leanon (리논)","link":"https://poclanos.com/album/celebrate/","retrieved":1710299504170,"image":"https://poclanos.com/drmvsn/wp-content/uploads/2024/03/4.-%EC%95%A8%EB%B2%94-%EC%BB%A4%EB%B2%84-leanon-%EB%A6%AC%EB%85%BC-Celebrate-600x600.jpg"},{"title":"table #2","contents":"orange flavored cigarettes","link":"https://poclanos.com/album/table-2/","retrieved":1710299504173,"image":"https://poclanos.com/drmvsn/wp-content/uploads/2024/03/04.-%EC%BB%A4%EB%B2%84-orange-flavored-cigarettes-table-_2-600x600.jpg"},{"title":"광합성","contents":"사라카야콤슨 (SarahKayaComson)","link":"https://poclanos.com/album/%ea%b4%91%ed%95%a9%ec%84%b1/","retrieved":1710234730846,"image":"https://poclanos.com/drmvsn/wp-content/uploads/2024/03/4.-%EC%95%A8%EB%B2%94%EC%BB%A4%EB%B2%84-%EC%82%AC%EB%9D%BC%EC%B9%B4%EC%95%BC%EC%BD%A4%EC%8A%A8-SarahKayaComson-%EA%B4%91%ED%95%A9%EC%84%B1-600x600.jpg"},{"title":"Solitude","contents":"Iwamizu","link":"https://poclanos.com/album/solitude-2/","retrieved":1710213122446,"image":"https://poclanos.com/drmvsn/wp-content/uploads/2024/03/3.-%EC%95%A8%EB%B2%94%EC%BB%A4%EB%B2%84-iwamizu-Solitude-600x600.jpg"},{"title":"Cherry Soap","contents":"About Paul","link":"https://poclanos.com/album/cherry-soap/","retrieved":1710213122447,"image":"https://poclanos.com/drmvsn/wp-content/uploads/2024/03/%EC%8D%B8%EB%84%A4%EC%9D%BC-ONENESS-Colors-600x600.jpg"},{"title":"Colors (KoozieSet EP Remix)","contents":"ONENESS","link":"https://poclanos.com/album/colors-koozieset-ep-remix/","retrieved":1710126715833,"image":"https://poclanos.com/drmvsn/wp-content/uploads/2024/03/4.-%EC%95%A8%EB%B2%94%EC%BB%A4%EB%B2%84-ONENESS-Colors-600x600.jpg"},{"title":"Segye","contents":"TENGGER","link":"https://poclanos.com/album/segye/","retrieved":1710126715833,"image":"https://poclanos.com/drmvsn/wp-content/uploads/2024/03/4.-%EC%95%A8%EB%B2%94%EC%BB%A4%EB%B2%84-TENGGER0-Segye-600x600.jpg"},{"title":"희망고문","contents":"D'svy","link":"https://poclanos.com/album/%ed%9d%ac%eb%a7%9d%ea%b3%a0%eb%ac%b8/","retrieved":1709953974192,"image":"https://poclanos.com/drmvsn/wp-content/uploads/2024/03/4.-%EC%95%A8%EB%B2%94%EC%BB%A4%EB%B2%84-Dsvy-%ED%9D%AC%EB%A7%9D%EA%B3%A0%EB%AC%B8-600x600.jpg"},{"title":"이 노래","contents":"PITTA (강형호)","link":"https://poclanos.com/album/%ec%9d%b4-%eb%85%b8%eb%9e%98/","retrieved":1709871127005,"image":"https://poclanos.com/drmvsn/wp-content/uploads/2024/03/4.-%EC%95%A8%EB%B2%94%EC%BB%A4%EB%B2%84-PITTA-%EC%9D%B4-%EB%85%B8%EB%9E%98-600x600.jpg"},{"title":"THIS IS EMERGENCY","contents":"FunkySwat","link":"https://poclanos.com/album/this-is-emergency/","retrieved":1709867417820,"image":"https://poclanos.com/drmvsn/wp-content/uploads/2024/03/3.-%EC%95%A8%EB%B2%94%EC%BB%A4%EB%B2%84-FunkySwat-THIS-IS-EMERGENCY-600x600.jpg"},{"title":"HANAMI","contents":"01SYNTH","link":"https://poclanos.com/album/hanami/","retrieved":1709780990056,"image":"https://poclanos.com/drmvsn/wp-content/uploads/2024/03/%ED%8F%AC%EB%A7%B7%EB%B3%80%ED%99%98COVER_HANAMI_01SYNTH-600x600.jpg"},{"title":"Default","contents":"a 9uy","link":"https://poclanos.com/album/default-2/","retrieved":1709780990057,"image":"https://poclanos.com/drmvsn/wp-content/uploads/2024/03/4.-%EC%95%A8%EB%B2%94%EC%95%84%ED%8A%B8-KIHU-a-9uy-Default-600x600.jpg"},{"title":"Eternal Memories","contents":"몽니","link":"https://poclanos.com/album/eternal-memories/","retrieved":1709716222860,"image":"https://poclanos.com/drmvsn/wp-content/uploads/2024/03/4.-%EC%95%A8%EB%B2%94%EC%BB%A4%EB%B2%84-%EB%AA%BD%EB%8B%88-Eternal-Memories-600x600.jpg"},{"title":"오뉴뉴슈퍼월드","contents":"오열 (OYEOL)","link":"https://poclanos.com/album/%ec%98%a4%eb%89%b4%eb%89%b4%ec%8a%88%ed%8d%bc%ec%9b%94%eb%93%9c/","retrieved":1709694637904,"image":"https://poclanos.com/drmvsn/wp-content/uploads/2024/02/4.-%EC%95%A8%EB%B2%94%EC%BB%A4%EB%B2%84-%EC%98%A4%EC%97%B4-%EC%98%A4%EB%89%B4%EB%89%B4%EC%8A%88%ED%8D%BC%EC%9B%94%EB%93%9C-600x600.jpg"},{"title":"Two Lovers","contents":"onthedal","link":"https://poclanos.com/album/two-lovers/","retrieved":1709694637905,"image":"https://poclanos.com/drmvsn/wp-content/uploads/2024/02/4.-%EC%95%A8%EB%B2%94%EC%BB%A4%EB%B2%84-onthedal-%EB%B0%95%ED%95%9C-Two-Lovers-600x600.jpg"},{"title":"One for the what.","contents":"ONENESS","link":"https://poclanos.com/album/one-for-the-what/","retrieved":1709608247354,"image":"https://poclanos.com/drmvsn/wp-content/uploads/2024/02/4.-%EC%95%A8%EB%B2%94%EC%BB%A4%EB%B2%84-ONENESS-One-for-the-what-600x600.jpg"},{"title":"침을 꼴딱","contents":"김오키","link":"https://poclanos.com/album/%ec%b9%a8%ec%9d%84-%ea%bc%b4%eb%94%b1/","retrieved":1709608247358,"image":"https://poclanos.com/drmvsn/wp-content/uploads/2024/02/4.-%EC%95%A8%EB%B2%94%EC%BB%A4%EB%B2%84-%EA%B9%80%EC%98%A4%ED%82%A4-%EC%B9%A8%EC%9D%84-%EA%BC%B4%EB%94%B1-600x600.jpg"},{"title":"Heavy","contents":"서현수","link":"https://poclanos.com/album/heavy/","retrieved":1709608247359,"image":"https://poclanos.com/drmvsn/wp-content/uploads/2024/02/4.-%EC%95%A8%EB%B2%94%EC%BB%A4%EB%B2%84-%EC%84%9C%ED%98%84%EC%88%98-Heavy-600x600.jpg"}]}