{"title":"POCLANOS ─ Album","url":"https://poclanos.com/album-list/","favicon":"https://poclanos.com/drmvsn/wp-content/uploads/2020/08/Android-Chrome-home_196x196-96x96.png","elements":[{"title":"EVERMOON","contents":"문미향","link":"https://poclanos.com/album/evermoon/","retrieved":1739697090363,"image":"https://poclanos.com/drmvsn/wp-content/uploads/2025/02/4.-%EC%BB%A4%EB%B2%84-%EB%AC%B8%EB%AF%B8%ED%96%A5-EVERMOON-600x600.jpg"},{"title":"아침이 널 쫓기 전에","contents":"Haru Kid (하루키드)","link":"https://poclanos.com/album/%ec%95%84%ec%b9%a8%ec%9d%b4-%eb%84%90-%ec%ab%93%ea%b8%b0-%ec%a0%84%ec%97%90/","retrieved":1739589336758,"image":"https://poclanos.com/drmvsn/wp-content/uploads/2025/02/4.-%EC%95%84%ED%8A%B8%EC%9B%8C%ED%81%AC-Haru-Kid-%ED%95%98%EB%A3%A8%ED%82%A4%EB%93%9C-%EC%95%84%EC%B9%A8%EC%9D%B4-%EB%84%90-%EC%AB%93%EA%B8%B0-%EC%A0%84%EC%97%90-600x600.jpg"},{"title":"바보","contents":"유령서점","link":"https://poclanos.com/album/%eb%b0%94%eb%b3%b4/","retrieved":1739502989625,"image":"https://poclanos.com/drmvsn/wp-content/uploads/2025/02/4.-%EC%BB%A4%EB%B2%84-%EC%9C%A0%EB%A0%B9%EC%84%9C%EC%A0%90-%EB%B0%94%EB%B3%B4-%EC%95%A8%EB%B2%94%EC%BB%A4%EB%B2%84-600x600.jpg"},{"title":"춘향팔자","contents":"황은진","link":"https://poclanos.com/album/%ec%b6%98%ed%96%a5%ed%8c%94%ec%9e%90/","retrieved":1739502989632,"image":"https://poclanos.com/drmvsn/wp-content/uploads/2025/02/4.-%EC%BB%A4%EB%B2%84-%ED%99%A9%EC%9D%80%EC%A7%84-%EC%B6%98%ED%96%A5%ED%8C%94%EC%9E%90-600x600.jpg"},{"title":"Stars","contents":"Rosie","link":"https://poclanos.com/album/stars-2/","retrieved":1739502989632,"image":"https://poclanos.com/drmvsn/wp-content/uploads/2025/02/5.-%EC%95%A8%EB%B2%94%EC%BB%A4%EB%B2%84-Rosie-Stars-600x600.jpg"},{"title":"By The Time","contents":"Kevin Kaho Tsui","link":"https://poclanos.com/album/by-the-time/","retrieved":1739416577869,"image":"https://poclanos.com/drmvsn/wp-content/uploads/2025/02/4.-%EC%BB%A4%EB%B2%84-By-The-Time-Cover-Artwork-600x600.jpg"},{"title":"HEADBUTTERS","contents":"Hakm","link":"https://poclanos.com/album/headbutters/","retrieved":1739416577870,"image":"https://poclanos.com/drmvsn/wp-content/uploads/2025/02/4.-%EC%95%A8%EB%B2%94%EC%BB%A4%EB%B2%84-%EB%9D%BC%EB%94%94%EC%98%A4939-HAKM-HEADBUTTERS-%EC%88%98%EC%A0%95-600x600.jpg"},{"title":"들키고 싶은 비밀","contents":"크리스탈 티","link":"https://poclanos.com/album/%eb%93%a4%ed%82%a4%ea%b3%a0-%ec%8b%b6%ec%9d%80-%eb%b9%84%eb%b0%80/","retrieved":1739351609082,"image":"https://poclanos.com/drmvsn/wp-content/uploads/2025/02/4.-%EC%95%A8%EB%B2%94%EC%BB%A4%EB%B2%84-%ED%81%AC%EB%A6%AC%EC%8A%A4%ED%83%88-%ED%8B%B0-%EB%93%A4%ED%82%A4%EA%B3%A0-%EC%8B%B6%EC%9D%80-%EB%B9%84%EB%B0%80-600x600.jpg"},{"title":"Smile! You’re On Camera (Special Edition)","contents":"Juju B. Goode (주주비굿)","link":"https://poclanos.com/album/smile-youre-on-camera-special-edition/","retrieved":1739243804458,"image":"https://poclanos.com/drmvsn/wp-content/uploads/2025/02/4.-%EC%95%A8%EB%B2%94%EC%BB%A4%EB%B2%84-Juju-B.-Goode-Smile-You_re-On-Camera_ARTWORK-600x600.jpg"},{"title":"어두워","contents":"zz_opp","link":"https://poclanos.com/album/%ec%96%b4%eb%91%90%ec%9b%8c/","retrieved":1739157463242,"image":"https://poclanos.com/drmvsn/wp-content/uploads/2025/02/4.-%EC%95%A8%EB%B2%94%EC%BB%A4%EB%B2%84-zz_opp-%EC%96%B4%EB%91%90%EC%9B%8C-600x600.jpg"},{"title":"불편한 잠","contents":"손서정","link":"https://poclanos.com/album/%eb%b6%88%ed%8e%b8%ed%95%9c-%ec%9e%a0/","retrieved":1739157463252,"image":"https://poclanos.com/drmvsn/wp-content/uploads/2025/02/4.-%EC%95%A8%EB%B2%94-%EC%BB%A4%EB%B2%84-%EC%86%90%EC%84%9C%EC%A0%95-%EB%B6%88%ED%8E%B8%ED%95%9C-%EC%9E%A0-600x600.jpeg"},{"title":"일기장","contents":"정비","link":"https://poclanos.com/album/%ec%9d%bc%ea%b8%b0%ec%9e%a5/","retrieved":1739157463253,"image":"https://poclanos.com/drmvsn/wp-content/uploads/2025/02/%EC%A0%95%EB%B9%84-EP-%EC%9D%BC%EA%B8%B0%EC%9E%A5-%EC%95%A8%EB%B2%94%EC%95%84%ED%8A%B8-600x600.jpg"},{"title":"NE MAEUM","contents":"zoey","link":"https://poclanos.com/album/ne-maeum/","retrieved":1739071025485,"image":"https://poclanos.com/drmvsn/wp-content/uploads/2025/02/4.-%EC%BB%A4%EB%B2%84-zoey-NE-MAEUM-600x600.jpeg"},{"title":"Run","contents":"화노 (Hwanho)","link":"https://poclanos.com/album/run-4/","retrieved":1738984472162,"image":"https://poclanos.com/drmvsn/wp-content/uploads/2025/01/4.-%EC%BB%A4%EB%B2%84-%ED%99%94%EB%85%B8-Run-600x600.jpg"},{"title":"N.1","contents":"MNC","link":"https://poclanos.com/album/n-1/","retrieved":1738919580985,"image":"https://poclanos.com/drmvsn/wp-content/uploads/2025/01/4.-MNC_N.1_Album-Cover-600x600.jpg"},{"title":"COWBOY","contents":"PLAYGRXXND","link":"https://poclanos.com/album/cowboy/","retrieved":1738898212409,"image":"https://poclanos.com/drmvsn/wp-content/uploads/2025/01/4.-%EC%BB%A4%EB%B2%84-NVRMNDTHT-COWBOY-600x600.jpg"},{"title":"고요의 정원","contents":"이라온","link":"https://poclanos.com/album/%ea%b3%a0%ec%9a%94%ec%9d%98-%ec%a0%95%ec%9b%90/","retrieved":1738836782293,"image":"https://poclanos.com/drmvsn/wp-content/uploads/2025/02/%EA%B3%A0%EC%9A%94%EC%9D%98-%EC%A0%95%EC%9B%90-Solitude_%EC%95%A8%EB%B2%94%EC%BB%A4%EB%B2%84-600x600.jpg"},{"title":"Little Darling","contents":"Kevin Kaho Tsui","link":"https://poclanos.com/album/little-darling/","retrieved":1738811739063,"image":"https://poclanos.com/drmvsn/wp-content/uploads/2025/01/4.-%EC%BB%A4%EB%B2%84-Little-Darling-Cover-Artwork-600x600.jpg"},{"title":"Lonely Love Song","contents":"weirdweirdweird","link":"https://poclanos.com/album/lonely-love-song/","retrieved":1738811739067,"image":"https://poclanos.com/drmvsn/wp-content/uploads/2025/01/4.-%EC%BB%A4%EB%B2%84-weirdweirdweird-Lonely-Love-Song-Single-600x600.jpg"},{"title":"우리의 메아리","contents":"박찬영","link":"https://poclanos.com/album/%ec%9a%b0%eb%a6%ac%ec%9d%98-%eb%a9%94%ec%95%84%eb%a6%ac/","retrieved":1738746815812,"image":"https://poclanos.com/drmvsn/wp-content/uploads/2025/01/4.-%EC%95%A8%EB%B2%94%EC%BB%A4%EB%B2%84-%EB%B0%95%EC%B0%AC%EC%98%81-%EC%9A%B0%EB%A6%AC%EC%9D%98-%EB%A9%94%EC%95%84%EB%A6%AC-600x600.jpg"}]}