{"title":"POCLANOS ─ Album","url":"https://poclanos.com/album-list/","favicon":"https://poclanos.com/drmvsn/wp-content/uploads/2020/08/Android-Chrome-home_196x196-96x96.png","elements":[{"title":"Woo-Woo-Ah-Ah","contents":"까데호","link":"https://poclanos.com/album/woo-woo-ah-ah/","retrieved":1726542839182,"image":"https://poclanos.com/drmvsn/wp-content/uploads/2024/09/%ED%81%AC%EA%B8%B0%EC%88%98%EC%A0%95-4.-%EC%95%A8%EB%B2%94%EC%BB%A4%EB%B2%84-%EA%B9%8C%EB%8D%B0%ED%98%B8-Woo-Woo-Ah-Ah-600x600.jpg"},{"title":"What You Want","contents":"nnn","link":"https://poclanos.com/album/what-you-want/","retrieved":1726542839182,"image":"https://poclanos.com/drmvsn/wp-content/uploads/2024/09/4.%EC%95%A8%EB%B2%94%EC%BB%A4%EB%B2%84-nnn-What-You-Want-600x600.jpg"},{"title":"Mirror (feat. 한지원 of Youth Hostel)","contents":"jumin","link":"https://poclanos.com/album/mirror-feat-%ed%95%9c%ec%a7%80%ec%9b%90-of-youth-hostel/","retrieved":1726542839185,"image":"https://poclanos.com/drmvsn/wp-content/uploads/2024/09/4.-%EC%95%A8%EB%B2%94-%EC%BB%A4%EB%B2%84-jumin-Mirror-feat.-%ED%95%9C%EC%A7%80%EC%9B%90-of-Youth-Hostel-600x600.jpg"},{"title":"모양들","contents":"모양들","link":"https://poclanos.com/album/%eb%aa%a8%ec%96%91%eb%93%a4/","retrieved":1726456814882,"image":"https://poclanos.com/drmvsn/wp-content/uploads/2024/09/4.-%EC%95%A8%EB%B2%94%EC%95%84%ED%8A%B8-%EB%AA%A8%EC%96%91%EB%93%A4-%EB%AA%A8%EC%96%91%EB%93%A4-600x600.jpg"},{"title":"멀어진 친구에게","contents":"강진아","link":"https://poclanos.com/album/%eb%a9%80%ec%96%b4%ec%a7%84-%ec%b9%9c%ea%b5%ac%ec%97%90%ea%b2%8c/","retrieved":1726456814881,"image":"https://poclanos.com/drmvsn/wp-content/uploads/2024/09/4.-%EC%95%A8%EB%B2%94%EC%BB%A4%EB%B2%84-%EA%B0%95%EC%A7%84%EC%95%84-%EB%A9%80%EC%96%B4%EC%A7%84-%EC%B9%9C%EA%B5%AC%EC%97%90%EA%B2%8C-600x600.jpg"},{"title":"이 밤에 이 맘에","contents":"장수빈","link":"https://poclanos.com/album/%ec%9d%b4-%eb%b0%a4%ec%97%90-%ec%9d%b4-%eb%a7%98%ec%97%90/","retrieved":1726370286694,"image":"https://poclanos.com/drmvsn/wp-content/uploads/2024/09/4.-%EC%95%A8%EB%B2%94%EC%BB%A4%EB%B2%84-%EC%9E%A5%EC%88%98%EB%B9%88-%EC%9D%B4-%EB%B0%A4%EC%97%90-%EC%9D%B4-%EB%A7%98%EC%97%90%EC%88%98%EC%A0%95-600x600.jpg"},{"title":"다이얼","contents":"까치산","link":"https://poclanos.com/album/%eb%8b%a4%ec%9d%b4%ec%96%bc/","retrieved":1726283626840,"image":"https://poclanos.com/drmvsn/wp-content/uploads/2024/09/4.-%EC%BB%A4%EB%B2%84-%EA%B9%8C%EC%B9%98%EC%82%B0-%EB%8B%A4%EC%9D%B4%EC%96%BC-600x600.jpg"},{"title":"봄을 기다리며","contents":"조종근","link":"https://poclanos.com/album/%eb%b4%84%ec%9d%84-%ea%b8%b0%eb%8b%a4%eb%a6%ac%eb%a9%b0/","retrieved":1726197231465,"image":"https://poclanos.com/drmvsn/wp-content/uploads/2024/09/4.-%EC%BB%A4%EB%B2%84-%EC%A1%B0%EC%A2%85%EA%B7%BC-%EB%B4%84%EC%9D%84-%EA%B8%B0%EB%8B%A4%EB%A6%AC%EB%A9%B0-600x600.jpg"},{"title":"JEWELS (Feat. Neidi)","contents":"a 9uy","link":"https://poclanos.com/album/jewels-feat-neidi/","retrieved":1726197231471,"image":"https://poclanos.com/drmvsn/wp-content/uploads/2024/09/4.-%EC%95%A8%EB%B2%94%EC%95%84%ED%8A%B8-KIHU-a-9uy-JEWELS-Feat.-Neidi-600x600.jpg"},{"title":"8","contents":"신세하 (Xin Seha)","link":"https://poclanos.com/album/8-2/","retrieved":1726197231472,"image":"https://poclanos.com/drmvsn/wp-content/uploads/2024/09/4.%EC%95%A8%EB%B2%94%EC%BB%A4%EB%B2%84-Xin-Seha-%EC%8B%A0%EC%84%B8%ED%95%98-8-600x600.jpeg"},{"title":"I Love You","contents":"결 (KYUL)","link":"https://poclanos.com/album/i-love-you-2/","retrieved":1726132360707,"image":"https://poclanos.com/drmvsn/wp-content/uploads/2024/09/4.-%EC%95%A8%EB%B2%94%EC%BB%A4%EB%B2%84-%EA%B2%B0-KYUL-I-Love-You-600x600.jpg"},{"title":"SOMEBODY HELP ME","contents":"Nutty","link":"https://poclanos.com/album/somebody-help-me/","retrieved":1726110815462,"image":"https://poclanos.com/drmvsn/wp-content/uploads/2024/09/4.-%EC%95%A8%EB%B2%94%EC%BB%A4%EB%B2%84-Nutty-SOMEBODY-HELP-ME-600x600.jpg"},{"title":"The Analog","contents":"강한국","link":"https://poclanos.com/album/the-analog/","retrieved":1726110815462,"image":"https://poclanos.com/drmvsn/wp-content/uploads/2024/09/4.-%EC%95%A8%EB%B2%94%EC%BB%A4%EB%B2%84-%EA%B0%95%ED%95%9C%EA%B5%AD-The-Analog-600x600.jpg"},{"title":"Season 14 Round 1 Cypher","contents":"Super Rookie Challenge","link":"https://poclanos.com/album/season-14-round-1-cypher/","retrieved":1726110815463,"image":"https://poclanos.com/drmvsn/wp-content/uploads/2024/09/4.-%EC%BB%A4%EB%B2%84-Super-Rookie-Challenge-Season-14-Round-1-Cypher-600x600.jpg"},{"title":"작은 숲","contents":"Room306","link":"https://poclanos.com/album/%ec%9e%91%ec%9d%80-%ec%88%b2/","retrieved":1726046006722,"image":"https://poclanos.com/drmvsn/wp-content/uploads/2024/09/4.-%EC%BB%A4%EB%B2%84-Room306-%EC%9E%91%EC%9D%80-%EC%88%B2-600x600.jpg"},{"title":"낙원","contents":"김나은","link":"https://poclanos.com/album/%eb%82%99%ec%9b%90/","retrieved":1726024365465,"image":"https://poclanos.com/drmvsn/wp-content/uploads/2024/09/4.-%EC%95%A8%EB%B2%94%EC%BB%A4%EB%B2%84-%EA%B9%80%EB%82%98%EC%9D%80-%EB%82%99%EC%9B%90-600x600.jpeg"},{"title":"그네","contents":"오주하 (OH!JUHA)","link":"https://poclanos.com/album/%ea%b7%b8%eb%84%a4/","retrieved":1726024365471,"image":"https://poclanos.com/drmvsn/wp-content/uploads/2024/09/4.-%EC%95%A8%EB%B2%94%EC%BB%A4%EB%B2%84-%EC%98%A4%EC%A3%BC%ED%95%98-%EA%B7%B8%EB%84%A4-600x600.jpg"},{"title":"ALIVE","contents":"수잔","link":"https://poclanos.com/album/alive-4/","retrieved":1725938050189,"image":"https://poclanos.com/drmvsn/wp-content/uploads/2024/09/4.-%EC%95%A8%EB%B2%94%EC%BB%A4%EB%B2%84-%EC%88%98%EC%9E%94-ALIVE-%EC%9E%91%EC%9D%80-%EC%9A%A9%EB%9F%89-600x600.jpg"},{"title":"Pierrot le Fumeur","contents":"Teho","link":"https://poclanos.com/album/pierrot-le-fumeur/","retrieved":1725938050190,"image":"https://poclanos.com/drmvsn/wp-content/uploads/2024/09/4.-%EC%95%A8%EB%B2%94%EC%BB%A4%EB%B2%84-Teho-Pierrot-le-Fumeur-600x600.jpg"},{"title":"There Is Not Defined","contents":"SANGHA","link":"https://poclanos.com/album/there-is-not-defined/","retrieved":1725938050190,"image":"https://poclanos.com/drmvsn/wp-content/uploads/2024/09/4.%EC%BB%A4%EB%B2%84-SANGHA-There-Is-Not-Defined-600x600.jpg"}]}